securitybreaches_data/Seccreds.py
securitybreaches_data/__init__.py
securitybreaches_data/hping.mascan.curlport.dud.colasofte.py
securitybreaches_data/nmap.netstat.supescan.nessus.wintrgen.snow.cleralog.audit.py
securitybreaches_data/recon.foca.ping.traccert.py
securitybreaches_data/securitybreachesnotes.docx
securitybreaches_data/socialengg.ddos.py
securitybreaches_data/webcopy.metasploit.whois.email.py
securitybreaches_jyoti-0.3.0.dist-info/licenses/LICENSE
securitybreaches_jyoti-0.3.0.dist-info/METADATA
securitybreaches_jyoti-0.3.0.dist-info/WHEEL
securitybreaches_jyoti-0.3.0.dist-info/top_level.txt
securitybreaches_jyoti-0.3.0.dist-info/RECORD
